byted_aurora_notebook_tool/__init__.py
byted_aurora_notebook_tool-0.0.1.dist-info/METADATA
byted_aurora_notebook_tool-0.0.1.dist-info/WHEEL
byted_aurora_notebook_tool-0.0.1.dist-info/top_level.txt
byted_aurora_notebook_tool-0.0.1.dist-info/RECORD
